test_template/__init__.py
tentativa_descricao-1.0.1.dist-info/LICENSE
tentativa_descricao-1.0.1.dist-info/METADATA
tentativa_descricao-1.0.1.dist-info/WHEEL
tentativa_descricao-1.0.1.dist-info/top_level.txt
tentativa_descricao-1.0.1.dist-info/RECORD
