Metadata-Version: 2.1
Name: tentativa-descricao
Version: 1.0.1
Summary: UNKNOWN
Home-page: UNKNOWN
Author: Helder
Author-email: helderprado@gmail.com
License: MIT
Keywords: teste
Platform: UNKNOWN
Classifier: Development Status :: 4 - Beta
Classifier: Environment :: Console
Classifier: Intended Audience :: Developers
Classifier: Intended Audience :: Information Technology
Classifier: Operating System :: Microsoft :: Windows
Classifier: Programming Language :: Python :: 3.3
Classifier: Programming Language :: Python :: 3.4
Classifier: Programming Language :: Python :: 3.5
Classifier: Programming Language :: Python :: 3.6
Classifier: Programming Language :: Python :: 3.7
